geopmdpy/VERSION
geopmdpy/__init__.py
geopmdpy/__main__.py
geopmdpy/access.py
geopmdpy/dbus_xml.py
geopmdpy/error.py
geopmdpy/gffi.py
geopmdpy/loop.py
geopmdpy/pio.py
geopmdpy/restorable_file_writer.py
geopmdpy/schemas.py
geopmdpy/service.py
geopmdpy/session.py
geopmdpy/shmem.py
geopmdpy/system_files.py
geopmdpy/topo.py
geopmdpy/version.py
geopmdpy-3.1.0.dist-info/AUTHORS
geopmdpy-3.1.0.dist-info/LICENSE-BSD-3-Clause
geopmdpy-3.1.0.dist-info/METADATA
geopmdpy-3.1.0.dist-info/WHEEL
geopmdpy-3.1.0.dist-info/entry_points.txt
geopmdpy-3.1.0.dist-info/top_level.txt
geopmdpy-3.1.0.dist-info/RECORD
